PyHAD/__init__.py
PyHAD/alignment.py
PyHAD/analysis.py
PyHAD/assignment.py
PyHAD/attributes.py
PyHAD/common.py
PyHAD/constants.py
PyHAD/container_base.py
PyHAD/container_common.py
PyHAD/creation.py
PyHAD/geometry.py
PyHAD/geostatistics.py
PyHAD/indexing.py
PyHAD/inout_common.py
PyHAD/lm_leastsquares.py
PyHAD/nl_leastquares.py
PyHAD/plotting.py
PyHAD/printing.py
PyHAD/removal.py
PyHAD/resampling.py
PyHAD/selection.py
PyHAD/ufuncs.py
PyHAD/units.py
PyHAD/variable.py
PyHAD/variables.py
pyhad-0.1.0.dist-info/LICENSE
pyhad-0.1.0.dist-info/METADATA
pyhad-0.1.0.dist-info/WHEEL
pyhad-0.1.0.dist-info/top_level.txt
pyhad-0.1.0.dist-info/RECORD
